{
  "1": {
    "events": [
      {
        "event": "取消文化的惩罚不公",
        "emotions": [
          {
            "state": "negative",
            "reason": "惩罚机制缺乏区分度，导致社会性死亡与罪行轻量化",
            "source_id": "2,3,4"
          }
        ]
      },
      {
        "event": "取消文化的系统性偏见",
        "emotions": [
          {
            "state": "negative",
            "reason": "针对女性/少数族裔的过度审查与白人特权",
            "source_id": "2,3"
          }
        ]
      },
      {
        "event": "取消文化的非宽容性",
        "emotions": [
          {
            "state": "negative",
            "reason": "拒绝接受观念改变与永久性惩罚机制",
            "source_id": "2,5"
          }
        ]
      }
    ]
  },
  "2": {
    "events": [
      {
        "event": "取消文化的社会矫正功能",
        "emotions": [
          {
            "state": "positive",
            "reason": "推动宗教歧视政策改革与性侵追责",
            "source_id": "1,3"
          }
        ]
      },
      {
        "event": "取消文化的赋权效应",
        "emotions": [
          {
            "state": "positive",
            "reason": "边缘群体通过反制言论获得政治话语权",
            "source_id": "3,4"
          }
        ]
      }
    ]
  },
  "3": {
    "events": [
      {
        "event": "被取消的个人经历",
        "emotions": [
          {
            "state": "negative",
            "reason": "慈善机构职务解除与社会贡献全面否定",
            "source_id": "1,2"
          },
          {
            "state": "neutral",
            "reason": "自我背景描述与特权缺失声明",
            "source_id": "self"
          }
        ]
      },
      {
        "event": "取消文化的暴民性质",
        "emotions": [
          {
            "state": "negative",
            "reason": "拒绝理性讨论与历史暴力延续",
            "source_id": "1,4"
          }
        ]
      }
    ]
  },
  "4": {
    "events": [
      {
        "event": "取消文化的宪法合法性",
        "emotions": [
          {
            "state": "positive",
            "reason": "最高法院认定反制言论受第一修正案保护",
            "source_id": "5,6"
          }
        ]
      },
      {
        "event": "取消文化的资本逻辑",
        "emotions": [
          {
            "state": "negative",
            "reason": "市场决策机制强化权力阶层审查",
            "source_id": "5,7"
          }
        ]
      }
    ]
  },
  "5": {
    "events": [
      {
        "event": "取消文化的程序正义缺失",
        "emotions": [
          {
            "state": "negative",
            "reason": "舆论压力导致仓促解雇与信任体系崩塌",
            "source_id": "2,3"
          }
        ]
      },
      {
        "event": "取消文化的寒蝉效应",
        "emotions": [
          {
            "state": "negative",
            "reason": "大学生/员工自我审查与敏感议题回避",
            "source_id": "4,6"
          }
        ]
      }
    ]
  },
  "6": {
    "events": [
      {
        "event": "取消文化的民主重构",
        "emotions": [
          {
            "state": "positive",
            "reason": "弱势群体通过舆论实现权力再分配",
            "source_id": "1,3"
          }
        ]
      }
    ]
  },
  "7": {
    "events": [
      {
        "event": "取消文化的过度报复循环",
        "emotions": [
          {
            "state": "negative",
            "reason": "惩罚机制缺乏比例原则与历史修正困境",
            "source_id": "2,5"
          }
        ]
      }
    ]
  },
  "8": {
    "events": [
      {
        "event": "取消文化的市场适应性",
        "emotions": [
          {
            "state": "neutral",
            "reason": "个人偏好作为市场竞争的自然组成部分",
            "source_id": "4,6"
          },
          {
            "state": "negative",
            "reason": "法律单一约束导致社会信用体系风险",
            "source_id": "5,7"
          }
        ]
      }
    ]
  }
}