[
    {
        "sentence": "是让历史的课堂更有思想，更有情怀，其实更有思想，这个并不是历史教学的一个新话题。",
        "Holder": "1",
        "Target": "历史教学",
        "Aspect": "思想性",
        "Opinion": "不是新话题",
        "Sentiment": "neutral",
        "Rationale": "提到这个话题已经被多次讨论"
    },
    {
        "sentence": "此前有很多的老师都谈过这样的话题，也有的老师出了以思想点亮课堂这样的专注，为什么我们今天还要谈这样的话题？",
        "Holder": "1",
        "Target": "历史教学话题",
        "Aspect": "重复性",
        "Opinion": "需要再次讨论",
        "Sentiment": "doubt",
        "Rationale": "虽然话题已被多次讨论，但仍需探讨其原因"
    },
    {
        "sentence": "我想首先我们会前热身的历史上也发有一期，它的主题叫寻找丢失的思想，他点出了我们今天确定这个主题非常重要的一个原因，是基于对我们今天课堂的一个观察，观察是什么？套用对学术界的一个评价，叫学问家突出，思想家淡出。",
        "Holder": "1",
        "Target": "课堂现状",
        "Aspect": "思想缺失",
        "Opinion": "学问家突出，思想家淡出",
        "Sentiment": "negative",
        "Rationale": "观察到课堂中思想缺失，学问家突出"
    },
    {
        "sentence": "我们今天的课堂材料多了，思想少了，这是一个可能很多老师都有感受的话题。",
        "Holder": "1",
        "Target": "课堂",
        "Aspect": "材料与思想的平衡",
        "Opinion": "材料多，思想少",
        "Sentiment": "negative",
        "Rationale": "课堂中材料增多而思想减少"
    },
    {
        "sentence": "我们开教育工作会议是我们学校的有一个老师在会议上特别忧虑的讲，他说我们作为一个老师，现在是不是要思考一个话题，就是在日益严酷的应试环境底下，我们还有没有保持自己思想的定力和能力？",
        "Holder": "1",
        "Target": "应试环境",
        "Aspect": "对教师思想的影响",
        "Opinion": "需要思考",
        "Sentiment": "negative",
        "Rationale": "应试环境严酷，影响教师思想的保持"
    },
    {
        "sentence": "他认为不管环境，特别是外在的环境如何的变化，你都可以选择成为你想成为的那样的人。",
        "Holder": "1",
        "Target": "个人选择",
        "Aspect": "环境与自我",
        "Opinion": "可以选择成为自己",
        "Sentiment": "positive",
        "Rationale": "认为个人选择不受环境影响"
    },
    {
        "sentence": "就像今天是第二节三江老师的课，他说在那样的一个时代，不同的人有不同的选择，你可以选择成为什么样的人？",
        "Holder": "1",
        "Target": "个人选择",
        "Aspect": "时代与选择",
        "Opinion": "可以选择",
        "Sentiment": "neutral",
        "Rationale": "提到不同时代有不同的选择"
    },
    {
        "sentence": "我们的那位老师他的答案就是在这样的一个时代，在个性受到了很多困扰的时代，只要你心中有梦，你有你的坚守，守住教育良心最后的一厘米主权，你仍然可以做一个可以点亮课堂思想发光的一个人。",
        "Holder": "1",
        "Target": "教师角色",
        "Aspect": "坚守与影响",
        "Opinion": "可以点亮课堂",
        "Sentiment": "positive",
        "Rationale": "认为心中有梦和坚守可以影响课堂"
    },
    {
        "sentence": "那么这个老师的发言也让我想到一本书，这本书的名字叫风暴中的北京四中，他是北岛主编的，里面有一篇文章，他来自于著名的导演陈凯歌，那个名字叫青春剑，这个青春剑不是朝气蓬勃之剑，不是觉醒年代中54青年飞扬的科学民主之剑，他是特定时代由于那个时候的教育思想所铸造的一柄有毒的剑，由于长期的锻造，让这把剑在剑匣里头急不可待，铮铮作响，就在等待一个时机，拔剑出鞘。",
        "Holder": "1",
        "Target": "青春剑",
        "Aspect": "象征意义",
        "Opinion": "有毒的剑",
        "Sentiment": "negative",
        "Rationale": "青春剑象征特定时代有毒的教育思想"
    },
    {
        "sentence": "最后那个时机来了，这些人他就成为走在那个时代前列的一群人，而那群人他是一个时代一个灾难揭开序幕的一个浪头，我觉得这一段历史应该给我们在座的哪位老师以非常深刻的启迪，我们不仅要思想找回丢失的思想，我们还要寻找怎样的思想去引领我们",
        "Holder": "1",
        "Target": "历史教训",
        "Aspect": "启迪与引领",
        "Opinion": "需要深刻启迪",
        "Sentiment": "positive",
        "Rationale": "认为历史教训能提供深刻启迪"
    }
]