[
    {
        "sentence": "把浏览器也放上是吧？您请坐您别动手。我早知道他做出这么丢人的事，我早该一巴掌打死他，我别不是给你说你做这种负责，给主任给老师赔礼道歉，说你错了，不需要你到时候给你机会了，不要了你电话，怎么又是这样的？你怎么不看看人家第一名是怎么学的？",
        "Holder": "1",
        "Target": "孩子",
        "Aspect": "行为和学习态度",
        "Opinion": "孩子行为丢人，学习态度不端正",
        "Sentiment": "negative",
        "Rationale": "孩子做出了丢人的事且不认真学习"
    },
    {
        "sentence": "吴老师给我打电话说你上次考试成绩下降了题，这事你总是告诉你，你不清楚了，吃个饭还是前一天你和爸爸聊了一晚上，我一晚上没睡着吗？跟你成绩下降有关系吗？你考不好是不是还赖我了，你翻我抽屉。",
        "Holder": "1",
        "Target": "孩子",
        "Aspect": "成绩下降的原因",
        "Opinion": "孩子找借口，推卸责任",
        "Sentiment": "negative",
        "Rationale": "孩子把成绩下降归咎于家长"
    },
    {
        "sentence": "对是现在都什么节骨眼了，不要再想这些七七八八的了，你是不是舍不得扔了？没关系，你妈我替你扔了，我全给你扔了，你这什么态度？",
        "Holder": "1",
        "Target": "孩子的物品",
        "Aspect": "处理杂物的态度",
        "Opinion": "孩子不舍得扔东西",
        "Sentiment": "negative",
        "Rationale": "孩子不舍得扔掉杂物，影响学习"
    },
    {
        "sentence": "你知不知道你现在转到文科来了，你没有别的退路，你只能当第一，不能当第，二是我去找了你吴老师，让他选你当班长，我不爱管事儿，你只有当了班长你才会重视你才会重视你妈，我太高了，不想活得这么累，等你考上北大，想怎么放松就怎么放松，想怎么玩就怎么玩，现在高考是你的唯一选择，你别无选择了，能不能别再指挥我了？小红书。",
        "Holder": "1",
        "Target": "孩子的未来规划",
        "Aspect": "学习和目标设定",
        "Opinion": "孩子必须全力以赴，考上北大",
        "Sentiment": "negative",
        "Rationale": "孩子没有全力以赴，家长感到焦虑和无奈"
    }
]