[
    {
        "sentence": "我想问一下日久生情，万一日久了生不了情咋办？",
        "Holder": "1",
        "Target": "日久生情",
        "Aspect": "情感产生的可能性",
        "Opinion": "担心生不了情",
        "Sentiment": "doubt",
        "Rationale": "对日久生情这一说法存在疑虑，担心时间长了也产生不了感情"
    },
    {
        "sentence": "那就是不够久。",
        "Holder": "2",
        "Target": "日久生情",
        "Aspect": "时间的长短",
        "Opinion": "时间不够长",
        "Sentiment": "neutral",
        "Rationale": "认为时间还不够长"
    },
    {
        "sentence": "一年日了不够久，再日一年，两年不够久，就2234再来一次，日完了一辈子发现还是生不了情。",
        "Holder": "1",
        "Target": "日久生情",
        "Aspect": "时间的长短与效果",
        "Opinion": "长时间也可能生不了情",
        "Sentiment": "negative",
        "Rationale": "担心即使花费很长时间也未必能产生感情"
    },
    {
        "sentence": "相亲了。我跟他第一眼见面不合适，我相下一位不行吗？",
        "Holder": "2",
        "Target": "相亲",
        "Aspect": "选择的权利",
        "Opinion": "可以换人",
        "Sentiment": "positive",
        "Rationale": "认为相亲过程中有权选择更合适的人"
    },
    {
        "sentence": "可以，这一位不行，一再下一位不行还再下一位，如果你发现他就是不喜欢，怎么办？",
        "Holder": "1",
        "Target": "相亲选择",
        "Aspect": "多次选择的结果",
        "Opinion": "担心一直找不到合适的人",
        "Sentiment": "doubt",
        "Rationale": "担心即使多次尝试也找不到合适的人"
    },
    {
        "sentence": "所以每一个都不喜欢吗？",
        "Holder": "2",
        "Target": "每一个对象",
        "Aspect": "喜欢与否",
        "Opinion": "怀疑每一个都不喜欢",
        "Sentiment": "ambiguous",
        "Rationale": "对每一个对象都没有明确表示喜欢"
    },
    {
        "sentence": "如果不喜欢是听大家说条件还不错，综合评分高，你再处处看，还是你再去换一个试一试？这不是你们相亲中也要面临的问题吗？",
        "Holder": "1",
        "Target": "相亲对象的选择",
        "Aspect": "选择的标准",
        "Opinion": "建议综合考虑",
        "Sentiment": "neutral",
        "Rationale": "提出了一个中立的建议，让大家综合考虑条件"
    },
    {
        "sentence": "当然是了，但是如果一见钟情的风险你知道是什么吗？你是爱过之后方知渣男。",
        "Holder": "2",
        "Target": "一见钟情",
        "Aspect": "风险",
        "Opinion": "认为一见钟情有风险",
        "Sentiment": "negative",
        "Rationale": "提到一见钟情可能导致爱上渣男"
    },
    {
        "sentence": "不一见钟情的风险是我们曾经在顶峰相见过，哪怕最后不爱了这份婚姻的结束，他也是曾经爱过的证据，但是相亲如果没有带带着百%的爱进去，你会觉得我没有爱过他，然后现在我还得离婚，这不是更亏吗？",
        "Holder": "1",
        "Target": "不一见钟情",
        "Aspect": "风险",
        "Opinion": "认为不一见钟情也有风险",
        "Sentiment": "negative",
        "Rationale": "提到不一见钟情可能导致没有真正爱过对方，最终离婚感觉更亏"
    },
    {
        "sentence": "不，你没爱过他，他伤不了你的心，最怕我们深爱过薇薇姐，那天你告诉我感情淡了，我问你我哪里错了？你说缘聚缘散了，我一生都在检讨当年我是不是瞎了。",
        "Holder": "2",
        "Target": "深爱过的人",
        "Aspect": "感情的结束",
        "Opinion": "认为深爱过的人更伤人",
        "Sentiment": "negative",
        "Rationale": "提到深爱过的人最终感情淡了，导致自己一直检讨"
    },
    {
        "sentence": "不，薇薇姐，你要知道所有青春的回旋镖都会有影响，爱和幸福，痛苦和幸福一定是同源的，你那么的痛苦就证明曾经你们相爱的时候是真的幸福，婚姻不是在讲持续的长度。",
        "Holder": "1",
        "Target": "青春的回旋镖",
        "Aspect": "爱情与痛苦的关系",
        "Opinion": "爱与痛苦同源",
        "Sentiment": "neutral",
        "Rationale": "强调爱与痛苦的同源性"
    },
    {
        "sentence": "对，所以是爱过的人才懂得不是以前结过的人才懂得，",
        "Holder": "2",
        "Target": "爱过的人",
        "Aspect": "对爱的理解",
        "Opinion": "爱过的人更懂得",
        "Sentiment": "positive",
        "Rationale": "认同爱过的人对爱的理解更深"
    },
    {
        "sentence": "可是如果你都没有爱过，却去跟他结不痛苦吗？你不曾幸福过，可能这一辈子都不曾幸福过。",
        "Holder": "1",
        "Target": "没有爱过的婚姻",
        "Aspect": "婚姻的幸福感",
        "Opinion": "没有爱过的婚姻是痛苦的",
        "Sentiment": "negative",
        "Rationale": "没有爱过的婚姻缺乏幸福感"
    },
    {
        "sentence": "也许你的人生有过痛苦，那是代表曾经你也曾经站在顶峰闪光过.",
        "Holder": "1",
        "Target": "人生的痛苦",
        "Aspect": "痛苦的意义",
        "Opinion": "痛苦代表曾经的辉煌",
        "Sentiment": "positive",
        "Rationale": "认为痛苦是曾经辉煌的象征"
    },
    {
        "sentence": "今天这个题目就是诉诸于个人情感，什么是婚姻，什么是幸福的婚姻，每个人都不一样，这几个人都结婚10多年了，我还没结婚，怎么可能会对幸福都有定义一样，但是殊途同归有一个共同点，我们对幸福的婚姻可以不一样的解读，但这个解读一定是要我自己做出来的，不是凑合的，不是将就的，是发自我内心的感受。",
        "Holder": "1",
        "Target": "幸福的婚姻",
        "Aspect": "个人情感与定义",
        "Opinion": "幸福的婚姻需个人内心感受",
        "Sentiment": "positive",
        "Rationale": "强调个人对幸福婚姻的定义和感受"
    },
    {
        "sentence": "学姐你好，谈恋爱一定要结婚吗？",
        "Holder": "3",
        "Target": "谈恋爱与结婚的关系",
        "Aspect": "必要性",
        "Opinion": "质疑谈恋爱必须结婚",
        "Sentiment": "neutral",
        "Rationale": "对谈恋爱是否一定要结婚有疑问"
    },
    {
        "sentence": "不一定，相亲也不一定结得了，婚都有失败率。",
        "Holder": "1",
        "Target": "结婚的可能性",
        "Aspect": "结婚的成功率",
        "Opinion": "结婚并非必然成功",
        "Sentiment": "neutral",
        "Rationale": "认识到结婚有失败的可能性"
    },
    {
        "sentence": "婚姻幸福等同于人生幸福吗？",
        "Holder": "3",
        "Target": "婚姻幸福与人生幸福的关系",
        "Aspect": "幸福的定义",
        "Opinion": "质疑等同性",
        "Sentiment": "neutral",
        "Rationale": "对婚姻幸福和人生幸福的关系存在疑问"
    },
    {
        "sentence": "不等于，婚姻的失败，也不一定等于人生的失败，有的可能时候婚姻的结束甚至是代表幸福人生的开始，所以这几个东西都不关联。",
        "Holder": "1",
        "Target": "婚姻幸福与人生幸福的关系",
        "Aspect": "幸福的独立性",
        "Opinion": "婚姻与人生幸福不关联",
        "Sentiment": "neutral",
        "Rationale": "认为婚姻的失败不一定影响人生的幸福，甚至可能是新幸福的开始"
    },
    {
        "sentence": "所以你刚才说没有爱过会后悔，那么我跟最适合谈恋爱的人一见钟情的人谈恋爱就好了，为什么一定要跟他结婚？",
        "Holder": "3",
        "Target": "谈恋爱与结婚的关系",
        "Aspect": "恋爱与婚姻的必要性",
        "Opinion": "质疑结婚的必要性",
        "Sentiment": "neutral",
        "Rationale": "对谈恋爱和结婚的必要性存在疑问"
    },
    {
        "sentence": "我们都说一句话叫做不以婚姻为目的的谈恋爱叫做耍流氓这句话，所以你觉得合理了，",
        "Holder": "1",
        "Target": "谈恋爱的目的",
        "Aspect": "恋爱目的的合理性",
        "Opinion": "支持以婚姻为目的的恋爱",
        "Sentiment": "neutral",
        "Rationale": "引用了普遍认同的观点来支持自己的看法"
    },
    {
        "sentence": "这是上个时代的说法，老实说我认为婚姻现在正在摆脱所谓的宗族结合，正在以自己为主，再也不存在什么我娶你嫁给我，我们两个都是为了我个人的成长和未来的陪伴，选了自己生活的战友而已。所以你也发现了，你刚才虽然告诉我说你不甘心，可是你不甘心的是你没爱过，你没有告诉我说人爱过就一定要跟这个人在当下结婚，这是第一件事情。我想问你第二件事情，你方今天全部的论点只有一个，叫做爱情是婚姻的必需品，请问爱情只有一种吗？",
        "Holder": "3",
        "Target": "婚姻的现代意义",
        "Aspect": "婚姻的个人成长与陪伴",
        "Opinion": "婚姻是个人选择而非传统束缚",
        "Sentiment": "neutral",
        "Rationale": "认为现代婚姻更注重个人成长和陪伴，而不是传统意义上的结合"
    },
    {
        "sentence": "爱情还能通过有恩情般的爱情，友情般的爱情吗？却要回到你刚才这个问题。你说我说不以结婚为目的的谈恋爱是耍流氓，你说是上个时代的，我想问一下相亲是哪个时代的产物？",
        "Holder": "1",
        "Target": "相亲",
        "Aspect": "相亲的时代背景",
        "Opinion": "质疑相亲的时代性",
        "Sentiment": "neutral",
        "Rationale": "对相亲的时代背景提出疑问"
    },
    {
        "sentence": "相亲是这个时代正在流行的产物，42%的青年人根据青山资本的调查，都在使用相亲和各种相亲软件正面回答我的问题，请问爱情只有一见钟情的激情这一种吗？",
        "Holder": "3",
        "Target": "相亲",
        "Aspect": "相亲的现代流行性",
        "Opinion": "相亲是现代流行的现象",
        "Sentiment": "neutral",
        "Rationale": "根据调查数据说明相亲的流行性"
    },
    {
        "sentence": "秋阳你先别着急，现代社会是42%的年轻人，那么请问300年前600年前1200年前是不是百%的年轻人都在使用相亲这件事情，父母之言媒妁之约相亲不是东亚文化，尤其是中国古代传下来的东西吗？你们今天还在宣扬这个东西叫不是在告诉你现在有相亲。",
        "Holder": "1",
        "Target": "相亲",
        "Aspect": "相亲的历史和文化背景",
        "Opinion": "相亲有深厚的历史文化渊源",
        "Sentiment": "neutral",
        "Rationale": "指出相亲在历史和文化中的地位"
    },
    {
        "sentence": "所以我方观点同意，我现在告诉你的是现在我们的婚姻观跟过去可以有不一样，如果你要用婚姻观来论证的话，浪漫之爱是中世纪骑士之爱才出现的概念，而且那时候专指的是婚外情，100年前我们还没有所谓的自由恋爱这个概念，您方立场根本不存在，所以不要谈历史，你正面回答我的问题，究竟爱情是不是只有一见钟情的激情爱这一种。",
        "Holder": "3",
        "Target": "爱情观念",
        "Aspect": "爱情观念的历史演变",
        "Opinion": "爱情观念随时代变化",
        "Sentiment": "neutral",
        "Rationale": "指出爱情观念在不同历史时期的差异"
    },
    {
        "sentence": "是100年前才有的自由恋爱，所以现在是怎么样？要返祖吗？",
        "Holder": "1",
        "Target": "自由恋爱",
        "Aspect": "自由恋爱的现代意义",
        "Opinion": "质疑回归传统恋爱观念",
        "Sentiment": "neutral",
        "Rationale": "对现代是否应回归传统恋爱观念提出疑问"
    },
    {
        "sentence": "所以不要说我再着急了，谁逃问题谁着急你也听出来了，爱情不止那一种，我们接下来就来聊一聊，你刚才告诉我说您方有些时候可以跟一见钟情的人也慢慢磨合出日久生情非常好，当我们排除了一开始激情的影响，我们要跟一个人慢慢在相处当中不断发现出他的优点，才能够一见钟才能够日久生情。请问这更依赖于条件的匹配还是开始的激情，如果一开始虽然一见钟情了，但是后来发现价值观特别不合适，生活习惯特别不匹配，我更有可能日久生情，还是相看两厌。",
        "Holder": "3",
        "Target": "爱情观念",
        "Aspect": "一见钟情与日久生情的对比",
        "Opinion": "探讨两者关系",
        "Sentiment": "neutral",
        "Rationale": "在对爱情的不同形式进行理性探讨"
    },
    {
        "sentence": "秋阳也好，薇薇姐也好，今天你们去相亲市场做的叫做田野调查，你不是真的去相亲，看过片的人都知道了，看片的时候是爽的，拍那个片子的人不一定爽，他只是装作爽，各位我相过亲。我今年36岁没有结婚，30岁出头的那几年确实是当时有一些慌，因为确实之前没有想过自己到30岁还不结婚去过。",
        "Holder": "1",
        "Target": "相亲市场",
        "Aspect": "相亲的真实体验",
        "Opinion": "相亲并非表面看起来的那样",
        "Sentiment": "negative",
        "Rationale": "相亲市场的现实与表面现象不符"
    },
    {
        "sentence": "其实今天讨论辩题的时候，大家也知道像褚英这种非常对吧，男权形象的人一直在这说，有些他说王梅你这个条件应该不用去相亲，我跟你说相亲真的很有意思，不相你不知道自己原来这么不值钱，我有没有相过好的，我肯定是相过好的的。样样都很好，很匹配，人家对我应该也是有意思的，因为我们约了三顿饭，还看了一次电影，最后大哥出柜，没有开玩笑是真的祝他幸福，如果他现在看得到的话，有没有碰过诚心诚意想结婚的？有，真的有超诚心。",
        "Holder": "1",
        "Target": "相亲经历",
        "Aspect": "相亲对象的真诚度",
        "Opinion": "遇到过真诚的人",
        "Sentiment": "positive",
        "Rationale": "遇到过真心想结婚的人"
    },
    {
        "sentence": "我上来跟人家想了解一下，我说你最喜欢听什么歌，人家只关心我有没有北京户口，我说你最喜欢这个世界上的哪一个城市，他只关心我有没有房，我每个月房贷多少钱，这就是赤裸裸的相信。什么综合评分，什么性格谈吐修养，这一切建立在你们双方对于这些的匹配是要完整匹配的，这个价值排序不是你我决定的，我当然想找一个聊得来谈得妥的不是的，排序市场不是这样的。",
        "Holder": "1",
        "Target": "相亲市场的价值排序",
        "Aspect": "条件匹配的重要性",
        "Opinion": "批评条件匹配",
        "Sentiment": "negative",
        "Rationale": "相亲市场过于注重物质条件，忽视了情感和性格的匹配"
    },
    {
        "sentence": "这个排序市场是根据什么？想想我们父母在往上那一辈，那个时候相亲市场的顶端是什么？供销社的售货员铁饭碗，后来是什么？拆迁户对吧？拆了10套房，再然后大厂的p8程序员绝对金字塔尖的顶端，我是做金融的，我曾经的男同事们5年前绝对是相亲市场上的顶流，投行金融男，年薪百万，风光凛凛，现在如果你们在相亲市场问到他，你可以问问他，去年差旅的报销批下来了吗？这个价值排序不是你定的，是社会的浪潮定的，可是这个社会的浪潮变得有多快？朋友们你总觉得人心易变对不对？觉得渣男很多，觉得婚姻7年之痒你知道吗？中国中小企业的平均寿命是2.5年，就算我跟他结婚，他7年变心，这7年时间我熬死了三个中国民营企业家，谁更容易变？所有的这一切什么占有也好，契约也好，是建立在甲方和乙方的条件不会变的情况下，你怎么能保证不变？爱的人都有可能变，不爱的人变的时候他会怎么做？你确认吗？这样的人你敢把你的后背给他吗？这样的人在你生孩子的时候，你能让他决定保大还是保小吗？不害怕吗？",
        "Holder": "1",
        "Target": "社会价值排序的变化",
        "Aspect": "人心的易变",
        "Opinion": "质疑人心的稳定性",
        "Sentiment": "negative",
        "Rationale": "社会价值排序变化快且人心易变"
    },
    {
        "sentence": "相亲界今天在这说，其实这个话我特别讨厌，但是今天为了让大家知道什么是赤裸裸的相亲市场，我说一下这个话我只说一次非常的恶心，叫做女人好比圣诞树最美不过25，这就是相亲市场，女生朋友们20岁的妹妹们不会对这句话有特别深的理解的，到了我这个年纪你就知道，所以就是在侮辱人，有没有高端相亲，有方式迂回一点，对吧？他不会直接问你多少钱，他会看你戴什么牌子的手表，你的车钥匙是什么牌子的，是不是BB a你背的包是限量款还是常规款会看，这些本质是一样的。",
        "Holder": "1",
        "Target": "相亲市场的歧视",
        "Aspect": "对女性的年龄和物质条件的偏见",
        "Opinion": "批评相亲市场的歧视",
        "Sentiment": "negative",
        "Rationale": "相亲市场对女性存在年龄和物质条件的歧视"
    },
    {
        "sentence": "这个价值排序你交给别人了，你不是在你自己手上，说实话今天我方做得非常粗糙，纯爱战士恋爱脑老子就是要爱，如果我自己瞎了眼选错了人我认了，但是起码是我自己选的，我不想把这个选择权交给命运，因为我为生活已经低够了头。我努力的赚钱工作就是为了让自己在这件事情上有充足的选择权和充足的底气，不管多少岁，我只对我想说yes的人说yes，只想对我说no的人，对他们都说no，我为生活妥协了这么多，就是在这件事情上不妥协，我为生活让步了这么多，就是在这件事情上不能让步，因为我的父母我们的祖先努力了这么多年，让今天我可以对我自己说，我选择结婚也可以选择不结婚，但是这一切必须是我自己选的。",
        "Holder": "1",
        "Target": "个人选择权",
        "Aspect": "自主选择的重要性",
        "Opinion": "坚持自主选择",
        "Sentiment": "positive",
        "Rationale": "坚持自主选择是对个人努力的体现"
    },
    {
        "sentence": "5个字。相亲很恶心，一见钟情能不能幸福？我不知道相亲狗必须死，不就是这个意思吗？对不对？学姐举了很多例子，我也举一个例子告诉大家，有一些东西为什么在相亲当中的匹配超过了一见钟情，超过了财产，但是可以通过相亲的途径，通过彼此的匹配遇到我对你得到一个评价，这个评价让我很感动。",
        "Holder": "3",
        "Target": "相亲与一见钟情",
        "Aspect": "相亲与一见钟情的对比",
        "Opinion": "相亲也有其价值",
        "Sentiment": "negative",
        "Rationale": "对相亲持有负面看法，但在某些情况下也能得到正面评价"
    },
    {
        "sentence": "我现在正处于我人生31年的最低谷，我在这个阶段得到了一个对我来说很珍贵的评价，就是有人告诉我说发现你，在这么痛苦的时候，你没有酗酒，你没有不工作，你一边工作还一边读书，你甚至没有推掉一次出差，你在健身，你在控制饮食，你在努力的做那些你应该做的事情，我发现你是一个这样子的人，这让人觉得很可靠，所以有一天我们的公司也会倒闭，毕竟2.5年倒闭1个，我们应该已经倒闭4次了好。但是在任何浪潮低谷之中，我梁秋阳都会是这样一个可靠的人，你可以通过匹配，而不是对我一见钟情，就可以了解到刚才学姐告诉我们说，我们要把主动权掌握在自己手里，这就是正方想讲的选择一见钟情，才是交出去自己的主动权。",
        "Holder": "3",
        "Target": "个人品质",
        "Aspect": "可靠性",
        "Opinion": "强调可靠性",
        "Sentiment": "positive",
        "Rationale": "在低谷中仍保持可靠"
    },
    {
        "sentence": "什么意思？为什么一见钟情会给大家一种这么大的安定感？这么强的魅惑力，为什么？当对方说到你想想你要嫁给一个你不爱的人的时候，我们会觉得突然没来由的恐惧，如果这个人我不爱了，这个人不是老天指派让我爱上他的，我会觉得很不甘心，为什么？因为，期待一见钟情的人，本质上很多时候是在无法抛弃内心的一种托付意识。我想把我自己交给某个人，我想通过等待让命运带给我一个最好的安排，这个世界上对一切有情人，不管是男性还是女性，最大的谎言和陷阱不是相亲，而是让他们相信遇到对的人你会遇到的，然后你的人生就完事大吉了，但是这是最大的谎言，这是不存在的，这是不存在的，否则我们怎么解释，我们为什么一次又一次的爱上渣男渣女，爱上那些辜负我们的不对的人。",
        "Holder": "3",
        "Target": "一见钟情的心理机制",
        "Aspect": "托付意识",
        "Opinion": "批评一见钟情的幻想",
        "Sentiment": "negative",
        "Rationale": "一见钟情往往基于不现实的期待"
    },
    {
        "sentence": "什么叫做一见钟情？我给大家一个非常简单的解释，一见钟情的本质是你遇见了自己的创伤，可以理解吗？脆弱的人无法抵抗拥抱和抚慰，坚强的人高傲的人无法抵代奉承和共鸣，孤独的人没有办法抵抵抗抵抗一个伙伴，亲和的人没有办法抵抗另外一只快乐的小狗。我们每个人都有残缺而遇到相似的残缺，我们总会怦然心动，这是为什么很多时候我们总是会爱上那些不对的人，因为很多人在成长过程当中对于那些错误的相处模式充满了熟悉感，我们的原生家庭我们受到过的创伤和挫折带给了我们这些相处模式，所以我们总觉得与君初相见犹似故人归，可是那只是熟悉感，所谓的化学反应是我们的创伤带给我们永生的烙印，什么叫一见钟情？相信爱是一种感觉，什么叫做告别恋爱脑？不是要让大家不要去爱了，而是让大家明白爱是一种能力。",
        "Holder": "3",
        "Target": "一见钟情的本质",
        "Aspect": "心理创伤的影响",
        "Opinion": "一见钟情是心理创伤的反应",
        "Sentiment": "negative",
        "Rationale": "一见钟情往往与心理创伤相关"
    },
    {
        "sentence": "如果从今天开始我们要开始相亲了，不是告诉大家我们不要爱了，而是要告诉大家我们要更加主动的去爱上真的能带给我幸福的人，不要因为另一个人跟你不匹配，你还喜欢他，你就觉得这个才叫真爱，不是这个叫做你真的受过伤，有一天我们能够坦然地自然地爱上每一个优秀的值得的人，而不是仅仅靠着命运的分配和一见钟情的时候，我们才获得了真正的自由。大家想一想，一个英俊的一个高贵的品性，高尚的、勇于承诺的跟你有共同语言的人，仅仅因为缺少了某些命运的魔法和生活的配方，就没有办法跟他日久生情，遗憾的究竟是他还是我们呢？所以为什么我方对于相亲这么乐观很简单，因为我们相信爱不是一种感觉，爱是一种能力，我们可以看过很好的风景，但不必在风景区买房，我们未必拥有一个奇迹般的开始，但可以凭自己写出一个童话般的结局。",
        "Holder": "3",
        "Target": "相亲与真爱",
        "Aspect": "主动寻找真爱",
        "Opinion": "相亲是主动寻找真爱的方式",
        "Sentiment": "positive",
        "Rationale": "相信爱是一种能力，相亲是主动寻找真爱的方式"
    },
    {
        "sentence": "有人说一见钟情是见色起意，可是我见过比他好看的，见过气质比他好的，可是他们都给不了我那种唯独他才有的感觉，我将这种感觉称之为新的选择，也有人说日久生情才是灵魂和思想的契合，但是一见钟情后的日久生情才是绝杀。",
        "Holder": "4",
        "Target": "一见钟情与日久生情",
        "Aspect": "两者的结合",
        "Opinion": "一见钟情后的日久生情更完美",
        "Sentiment": "positive",
        "Rationale": "一见钟情后的日久生情结合了感觉和思想的契合"
    }
]